lti_toolbox/__init__.py
lti_toolbox/admin.py
lti_toolbox/apps.py
lti_toolbox/backend.py
lti_toolbox/exceptions.py
lti_toolbox/factories.py
lti_toolbox/launch_params.py
lti_toolbox/lti.py
lti_toolbox/models.py
lti_toolbox/utils.py
lti_toolbox/validator.py
lti_toolbox/views.py
lti_toolbox/migrations/0001_initial.py
lti_toolbox/migrations/0002_lticonsumer_url.py
lti_toolbox/migrations/__init__.py
django_lti_toolbox-2.0.0.dist-info/LICENSE
django_lti_toolbox-2.0.0.dist-info/METADATA
django_lti_toolbox-2.0.0.dist-info/WHEEL
django_lti_toolbox-2.0.0.dist-info/top_level.txt
django_lti_toolbox-2.0.0.dist-info/zip-safe
django_lti_toolbox-2.0.0.dist-info/RECORD
