Metadata-Version: 2.1
Name: django-lti-toolbox
Version: 2.0.0
Summary: A Django application to build LTI Tool Providers
Home-page: https://github.com/openfun/django-lti-toolbox
Author: Open FUN (France Universite Numerique)
Author-email: fun.dev@fun-mooc.fr
License: MIT
Keywords: Django,LTI
Platform: UNKNOWN
Classifier: Development Status :: 5 - Production/Stable
Classifier: Framework :: Django
Classifier: Intended Audience :: Developers
Classifier: License :: OSI Approved :: MIT License
Classifier: Natural Language :: English
Classifier: Programming Language :: Python :: 3
Classifier: Programming Language :: Python :: 3.8
License-File: LICENSE
Requires-Dist: Django
Requires-Dist: oauthlib (>=3.0.0)
Provides-Extra: ci
Requires-Dist: twine (==2.0.0) ; extra == 'ci'
Provides-Extra: dev
Requires-Dist: bandit (==1.6.2) ; extra == 'dev'
Requires-Dist: black (==22.3.0) ; extra == 'dev'
Requires-Dist: flake8 (==3.7.9) ; extra == 'dev'
Requires-Dist: ipdb (==0.12.2) ; extra == 'dev'
Requires-Dist: ipython (==7.9.0) ; extra == 'dev'
Requires-Dist: isort (==4.3.21) ; extra == 'dev'
Requires-Dist: mypy (==0.761) ; extra == 'dev'
Requires-Dist: pyfakefs (==3.7.1) ; extra == 'dev'
Requires-Dist: pylint-django (==2.0.13) ; extra == 'dev'
Requires-Dist: pylint (==2.4.4) ; extra == 'dev'
Requires-Dist: pytest-cov (==2.8.1) ; extra == 'dev'
Requires-Dist: pytest-django (==4.5.2) ; extra == 'dev'
Requires-Dist: pytest (==7.4.0) ; extra == 'dev'
Provides-Extra: sandbox
Requires-Dist: Django (==4.2.4) ; extra == 'sandbox'
Requires-Dist: django-configurations (==2.4.1) ; extra == 'sandbox'
Requires-Dist: factory-boy (==2.12.0) ; extra == 'sandbox'
Requires-Dist: psycopg2-binary (==2.8.4) ; extra == 'sandbox'
Requires-Dist: django-crispy-forms (==1.9.1) ; extra == 'sandbox'
